watchmen_cli/__init__.py
watchmen_cli/common/__init__.py
watchmen_cli/common/client.py
watchmen_cli/common/constants.py
watchmen_cli/common/exception.py
watchmen_cli/main.py
watchmen_cli/service/__init__.py
watchmen_cli/service/deployment.py
watchmen_cli/service/rerun.py
watchmen_cli/settings.py
watchmen_cli-18.0.1.dist-info/METADATA
watchmen_cli-18.0.1.dist-info/WHEEL
watchmen_cli-18.0.1.dist-info/RECORD
