Metadata-Version: 2.4
Name: watchmen-cli
Version: 18.0.1
Summary: 
License: MIT
Author: botlikes
Author-email: 75356972+botlikes456@users.noreply.github.com
Requires-Python: >=3.12,<3.13
Classifier: License :: OSI Approved :: MIT License
Classifier: Programming Language :: Python :: 3
Classifier: Programming Language :: Python :: 3.12
Requires-Dist: fire (>=0.6.0,<0.7.0)
Requires-Dist: requests (>=2.32.3,<3.0.0)
Requires-Dist: watchmen-utilities (==18.0.1)
